{
  "id": 26265,
  "accountName": "RadianceAnalyticsAccount1",
  "emailId": "pratyush.sunanda@highradius.com",
  "firstName": "Alan",
  "lastName": "Roy",
  "phone": "",
  "bucketNames": ["0-30", "31-60", "61-90", "\u003e91"],
  "asteriskConfig": {
    "asteriskIp": "calling-t.highradius.com",
    "iceServers": "[{\"url\":\"stun:stun.l.google.com:19302\"}]"
  },
  "currencyList": [],
  "workbookList": [
    102581542,
    102581544,
    102581545,
    102581546,
    102581548,
    102581549,
    102581550,
    102581552,
    102581553,
    102581555
  ],
  "customerNames": [
    "Permalink",
    "Max Power",
    "Weber Enterprises",
    "Rogers Group",
    "Allen Baker",
    "Flipkart",
    "Amazon",
    "Snapdeal",
    "ABC Products",
    "Walmart"
  ]
}
